[
{"sentence_id":150,"text_snippet":"The prohibition in the preceding sentence against using the Bi-annual Exception","tag":"OBLIGATION","confidence":"high"},
{"sentence_id":151,"text_snippet":"(4) Player Contracts signed pursuant to the Bi-annual Exception covering two (2)","tag":"OBLIGATION","confidence":"high"},
{"sentence_id":152,"text_snippet":"(5) The Bi-annual Exception for a Team, if applicable, shall arise on the first ","tag":"OBLIGATION","confidence":"high"},
{"sentence_id":153,"text_snippet":"(e) Non-Taxpayer Mid-Level Salary Exception.","tag":"COMMENT","confidence":"high"},
{"sentence_id":154,"text_snippet":"Subject to the rules set forth in Section 2(e) above and Section 6(n) below:","tag":"REFERENCE","confidence":"high"},
{"sentence_id":155,"text_snippet":"(1) A Team may use the Non-Taxpayer Mid-Level Salary Exception to sign and/or ac","tag":"THRESHOLD","confidence":"high"},
{"sentence_id":156,"text_snippet":"(2) The term of a Player Contract signed pursuant to the Non-Taxpayer Mid-Level ","tag":"THRESHOLD","confidence":"high"},
{"sentence_id":157,"text_snippet":"(3) A Team may not use all or any portion of the Non-Taxpayer Mid-Level Salary E","tag":"OBLIGATION","confidence":"high"},
{"sentence_id":158,"text_snippet":"(4) Player Contracts signed pursuant to the Non-Taxpayer Mid-Level Salary Except","tag":"OBLIGATION","confidence":"high"},
{"sentence_id":159,"text_snippet":"(5) Notwithstanding anything to the contrary in Section 6(e)(3) above, if a Vete","tag":"EXCEPTION","confidence":"high"},
{"sentence_id":160,"text_snippet":"(6) The Non-Taxpayer Mid-Level Salary Exception for a Team shall arise on the fi","tag":"OBLIGATION","confidence":"high"},
{"sentence_id":161,"text_snippet":"(f) Taxpayer Mid-Level Salary Exception.","tag":"COMMENT","confidence":"high"},
{"sentence_id":162,"text_snippet":"Subject to the rules set forth in Section 2(e) above and Section 6(n) below:","tag":"REFERENCE","confidence":"high"},
{"sentence_id":163,"text_snippet":"(1) A Team may use the Taxpayer Mid-Level Salary Exception to sign one (1) or mo","tag":"THRESHOLD","confidence":"high"},
{"sentence_id":164,"text_snippet":"|                                     | Taxpayer Mid-Level Salary Exception    ","tag":"THRESHOLD","confidence":"low"},
{"sentence_id":165,"text_snippet":"|-------------------------------------|------------------------------------------","tag":"COMMENT","confidence":"high"},
{"sentence_id":166,"text_snippet":"| For the 2023-24 Salary Cap Year     | $5 million                             ","tag":"THRESHOLD","confidence":"high"},
{"sentence_id":167,"text_snippet":"| For each subsequent Salary Cap Year | $5 million multiplied by a fraction, th","tag":"THRESHOLD","confidence":"high"},
{"sentence_id":168,"text_snippet":"(2) A Team may not use all or any portion of the Taxpayer Mid-Level Salary Excep","tag":"OBLIGATION","confidence":"high"},
{"sentence_id":169,"text_snippet":"(3) Player Contracts signed pursuant to the Taxpayer Mid-Level Salary Exception ","tag":"OBLIGATION","confidence":"high"},
{"sentence_id":170,"text_snippet":"(4) The Taxpayer Mid-Level Salary Exception for a Team shall arise on the first ","tag":"OBLIGATION","confidence":"high"},
{"sentence_id":171,"text_snippet":"(5) In the event that, during a Salary Cap Year, a Team: (i) does not use the No","tag":"CONDITION","confidence":"high"},
{"sentence_id":172,"text_snippet":"(g) Mid-Level Salary Exception for Room Teams.","tag":"COMMENT","confidence":"high"},
{"sentence_id":173,"text_snippet":"Subject to the rules set forth in Section 6(n) below:","tag":"REFERENCE","confidence":"high"},
{"sentence_id":174,"text_snippet":"(1) In the event (i) a Team's Team Salary at any time during a Salary Cap Year i","tag":"CONDITION","confidence":"high"},
{"sentence_id":175,"text_snippet":"(2) The term of a Player Contract signed pursuant to the Mid-Level Salary Except","tag":"THRESHOLD","confidence":"high"},
{"sentence_id":176,"text_snippet":"(3) Once a Team uses the Mid-Level Salary Exception for Room Teams during a Sala","tag":"OBLIGATION","confidence":"high"},
{"sentence_id":177,"text_snippet":"(4) Player Contracts signed pursuant to the Mid-Level Salary Exception for Room ","tag":"OBLIGATION","confidence":"high"},
{"sentence_id":178,"text_snippet":"(5) The Mid-Level Salary Exception for Room Teams for a Team shall: (i) arise on","tag":"OBLIGATION","confidence":"high"},
{"sentence_id":179,"text_snippet":"(i) Minimum Player Salary Exception.","tag":"COMMENT","confidence":"high"},
{"sentence_id":180,"text_snippet":"A Team may sign a player to, or acquire by assignment, a Player Contract, not to","tag":"OBLIGATION","confidence":"high"},
{"sentence_id":181,"text_snippet":"(j) Traded Player Exception.","tag":"COMMENT","confidence":"high"},
{"sentence_id":182,"text_snippet":"(1) Subject to the rules set forth in Section 6(n) below and Section 6(j)(6) bel","tag":"OBLIGATION","confidence":"high"},
{"sentence_id":183,"text_snippet":"(i) Standard Traded Player Exception.","tag":"COMMENT","confidence":"high"},
{"sentence_id":184,"text_snippet":"Subject to the rules set forth in Section 2(e) above, a Team may use the \"Standa","tag":"THRESHOLD","confidence":"high"},
{"sentence_id":185,"text_snippet":"(ii) Aggregated Standard Traded Player Exception.","tag":"COMMENT","confidence":"high"},
{"sentence_id":186,"text_snippet":"Subject to the rules set forth in Section 2(e) above, a Team may use the \"Aggreg","tag":"THRESHOLD","confidence":"high"},
{"sentence_id":187,"text_snippet":"(iii) Transition Traded Player Exception.","tag":"COMMENT","confidence":"high"},
{"sentence_id":188,"text_snippet":"During the 2023-24 Salary Cap Year only, and subject to the rules set forth in S","tag":"THRESHOLD","confidence":"high"},
{"sentence_id":189,"text_snippet":"(iv) Expanded Traded Player Exception.","tag":"COMMENT","confidence":"high"},
{"sentence_id":190,"text_snippet":"Subject to the rules set forth in Section 2(e) above, a Team may use the \"Expand","tag":"THRESHOLD","confidence":"high"},
{"sentence_id":191,"text_snippet":"(v) Room Under Salary Cap Plus $250,000.","tag":"COMMENT","confidence":"high"},
{"sentence_id":192,"text_snippet":"Except as provided in Section 6(j)(2) below, and notwithstanding Section 6(n) be","tag":"EXCEPTION","confidence":"high"},
{"sentence_id":193,"text_snippet":"For clarity, a Team that acquires one (1) or more players in accordance with thi","tag":"OBLIGATION","confidence":"high"},
{"sentence_id":194,"text_snippet":"(2) In lieu of conducting a trade in accordance with Section 6(j)(1)(v) above, a","tag":"EXCEPTION","confidence":"high"},
{"sentence_id":195,"text_snippet":"(3) Notwithstanding anything to the contrary in Section 6(j)(1) above, if a Team","tag":"EXCEPTION","confidence":"high"},
{"sentence_id":196,"text_snippet":"(4) Notwithstanding anything to the contrary in Section 6(j)(1) above, the follo","tag":"EXCEPTION","confidence":"high"},
{"sentence_id":197,"text_snippet":"(i) No player whose Player Contract was acquired pursuant to an Exception in the","tag":"OBLIGATION","confidence":"high"},
{"sentence_id":198,"text_snippet":"(ii) Other than during the period beginning on December 15 of a Salary Cap Year ","tag":"OBLIGATION","confidence":"high"},
{"sentence_id":199,"text_snippet":"For the purposes of this rule only, a \"Minimum Traded Player\" is a player whose ","tag":"DEFINITION","confidence":"high"}
]